LICENCE
MANIFEST.in
README.md
setup.py
pytassium/__init__.py
pytassium.egg-info/PKG-INFO
pytassium.egg-info/SOURCES.txt
pytassium.egg-info/dependency_links.txt
pytassium.egg-info/requires.txt
pytassium.egg-info/top_level.txt
scripts/pytassium