Metadata-Version: 1.0
Name: pytassium
Version: 0.2.7
Summary: A Python library for working with Kasabi.com APIs
Home-page: https://github.com/iand/pytassium
Author: Ian Davis
Author-email: nospam@iandavis.com
License: UNKNOWN
Platform: UNKNOWN
Classifier: Programming Language :: Python
Classifier: License :: Public Domain
Classifier: Operating System :: OS Independent
Classifier: Development Status :: 4 - Beta
Classifier: Intended Audience :: Developers
Classifier: Topic :: Software Development :: Libraries :: Python Modules
Classifier: Topic :: Database
